django_inet/__init__.py
django_inet/models.py
django_inet/rest.py
django_inet-1.1.0.dist-info/entry_points.txt
django_inet-1.1.0.dist-info/LICENSE.txt
django_inet-1.1.0.dist-info/WHEEL
django_inet-1.1.0.dist-info/METADATA
django_inet-1.1.0.dist-info/RECORD
